winontop/__init__.py
winontop/__main__.py
winontop/winontop.py
winontop-0.1.dist-info/DESCRIPTION.rst
winontop-0.1.dist-info/METADATA
winontop-0.1.dist-info/RECORD
winontop-0.1.dist-info/WHEEL
winontop-0.1.dist-info/entry_points.txt
winontop-0.1.dist-info/metadata.json
winontop-0.1.dist-info/top_level.txt
