Metadata-Version: 2.0
Name: winontop
Version: 0.1
Summary: An easy tool to keep windows on top of others.
Home-page: https://github.com/jithurjacob/winontop
Author: Jithu R Jacob
Author-email: jithurjacob@gmail.com
License: BSD
Download-URL: https://github.com/jithurjacob/winontop/tarball/0.1
Keywords: python windows top winontop windowsontop
Platform: UNKNOWN
Classifier: Development Status :: 3 - Alpha
Classifier: Topic :: Utilities
Classifier: Operating System :: Microsoft
Classifier: Environment :: Win32 (MS Windows)
Classifier: License :: OSI Approved :: BSD License
